simpml/__init__.py
simpml/py.typed
simpml/common/__init__.py
simpml/common/all.py
simpml/common/metrics_pool.py
simpml/common/models_pool.py
simpml/core/__init__.py
simpml/core/base.py
simpml/core/data_set.py
simpml/core/experiment_manager.py
simpml/core/loggers_pool.py
simpml/core/trainers_pool.py
simpml/tabular/__init__.py
simpml/tabular/adapters_pool.py
simpml/tabular/all.py
simpml/tabular/data_fetcher_pool.py
simpml/tabular/hyperparameters_optimizer.py
simpml/tabular/inference.py
simpml/tabular/interpreter.py
simpml/tabular/model.py
simpml/tabular/pipeline.py
simpml/tabular/shap_manager.py
simpml/tabular/splitter_pool.py
simpml/tabular/steps_pool.py
simpml/tabular/tabular_data_manager.py
simpml/utils/MlFlow.py
simpml/utils/__init__.py
simpml/vision/__init__.py
simpml/vision/all.py
simpml/vision/base.py
simpml/vision/data.py
simpml/vision/model.py
simpml/vision/splitter_pool.py
simpml/vision/utils.py
simpml-0.1.dist-info/LICENSE
simpml-0.1.dist-info/METADATA
simpml-0.1.dist-info/WHEEL
simpml-0.1.dist-info/top_level.txt
simpml-0.1.dist-info/RECORD
