Metadata-Version: 2.1
Name: simpml
Version: 0.1
Summary: SimpML is an open-source, no/low-code machine learning library in Python that simplifies and automates machine learning workflows.
Author: Miriam Horovicz, Roni Goldschmidt
Author-email: miryam.hor@gmail.com, ronigoldsmid@gmail.com
Classifier: Development Status :: 3 - Alpha
Classifier: Intended Audience :: Developers
Classifier: Intended Audience :: Science/Research
Classifier: License :: OSI Approved :: MIT License
Classifier: Programming Language :: Python :: 3.8
Classifier: Programming Language :: Python :: 3.9
Classifier: Programming Language :: Python :: 3.10
Classifier: Programming Language :: Python :: 3.11
Requires-Python: >=3.8.1,<3.12
License-File: LICENSE
Requires-Dist: alembic>=1.11.1
Requires-Dist: combo>=0.1.3
Requires-Dist: dill>=0.3.7
Requires-Dist: dtreeviz>=2.2.2
Requires-Dist: fastai>=2.7.12
Requires-Dist: feature-engine>=1.6.1
Requires-Dist: imbalanced-learn>=0.11.0
Requires-Dist: importlib-metadata>=6.8.0
Requires-Dist: ipython>=8.12.2
Requires-Dist: ipywidgets>=8.0.7
Requires-Dist: joblib>=1.3.1
Requires-Dist: lightgbm>=4.0.0
Requires-Dist: matplotlib>=3.7.2
Requires-Dist: methodtools>=0.4.7
Requires-Dist: mlflow>=2.5.0
Requires-Dist: numpy>=1.23.5
Requires-Dist: opencv-python>=4.8.0.74
Requires-Dist: openpyxl>=3.1.2
Requires-Dist: optuna>=3.2.0
Requires-Dist: packaging>=23.1
Requires-Dist: pandas>=2.0.3
Requires-Dist: patsy>=0.5.3
Requires-Dist: plotly>=5.15.0
Requires-Dist: pydataset>=0.2.0
Requires-Dist: pyod>=1.1.0
Requires-Dist: scikit-learn>=1.3.0
Requires-Dist: seaborn>=0.12.2
Requires-Dist: shap>=0.42.1
Requires-Dist: statsmodels>=0.14.0
Requires-Dist: termcolor>=2.3.0
Requires-Dist: tsfresh>=0.20.1
Requires-Dist: typing-extensions>=4.7.1
Requires-Dist: xgboost>=1.7.6
Requires-Dist: xlrd>=2.0.1
Provides-Extra: dev
Requires-Dist: black>=23.7.0; extra == "dev"
Requires-Dist: flake8>=6.1.0; extra == "dev"
Requires-Dist: flake8-bugbear>=23.7.10; extra == "dev"
Requires-Dist: flake8-builtins>=2.1.0; extra == "dev"
Requires-Dist: flake8-comprehensions>=3.14.0; extra == "dev"
Requires-Dist: flake8-docstrings>=1.7.0; extra == "dev"
Requires-Dist: flake8-import-order>=0.18.2; extra == "dev"
Requires-Dist: isort>=5.12.0; extra == "dev"
Requires-Dist: mypy>=1.5.1; extra == "dev"
Requires-Dist: pep8-naming>=0.13.3; extra == "dev"
Requires-Dist: poethepoet>=0.21.1; extra == "dev"
Requires-Dist: pytest>=7.4.0; extra == "dev"
Requires-Dist: pytest-cov>=4.1.0; extra == "dev"
Requires-Dist: pytest-dependency>=0.5.1; extra == "dev"
Requires-Dist: types-termcolor>=1.1.6.2; extra == "dev"
Requires-Dist: docutils>=0.18.1; extra == "dev"
Requires-Dist: GitPython>=3.1.32; extra == "dev"
Requires-Dist: nbsphinx>=0.9.2; extra == "dev"
Requires-Dist: pydata-sphinx-theme>=0.13.3; extra == "dev"
Requires-Dist: sphinx>=6.2.1; extra == "dev"
Requires-Dist: sphinxcontrib-jquery>=4.1; extra == "dev"
Requires-Dist: sphinx-autodoc-typehints>=1.23.0; extra == "dev"
Requires-Dist: sphinx-rtd-size>=0.2.0; extra == "dev"
Requires-Dist: sphinx-rtd-theme>=1.2.2; extra == "dev"
